sonq/__init__.py
sonq/cmd.py
sonq/operation.py
sonq/query.py
sonq-0.1.4.dist-info/METADATA
sonq-0.1.4.dist-info/WHEEL
sonq-0.1.4.dist-info/entry_points.txt
sonq-0.1.4.dist-info/top_level.txt
sonq-0.1.4.dist-info/RECORD
