Metadata-Version: 2.4
Name: sonq
Version: 0.1.4
Home-page: https://github.com/socrateslee/sonq
Author: Lichun
Classifier: Environment :: Console
Classifier: Intended Audience :: Developers
Classifier: License :: OSI Approved :: MIT License
Classifier: Programming Language :: Python
Requires-Dist: six
Requires-Dist: pymongo
Dynamic: author
Dynamic: classifier
Dynamic: home-page
Dynamic: requires-dist
